fhiry/__init__.py
fhiry/base_fhiry.py
fhiry/bqsearch.py
fhiry/fhirndjson.py
fhiry/fhirsearch.py
fhiry/fhiry.py
fhiry/flattenfhir.py
fhiry/main.py
fhiry/parallel.py
fhiry-5.2.2.dist-info/METADATA
fhiry-5.2.2.dist-info/WHEEL
fhiry-5.2.2.dist-info/entry_points.txt
fhiry-5.2.2.dist-info/licenses/LICENSE
fhiry-5.2.2.dist-info/RECORD
