Metadata-Version: 2.4
Name: fhiry
Version: 5.2.2
Summary: FHIR to pandas.dataframe for AI and ML
Project-URL: Homepage, https://dermatologist.github.io/fhiry/
Project-URL: Repository, https://github.com/dermatologist/fhiry
Project-URL: Documentation, https://dermatologist.github.io/fhiry/
Author-email: Bell Eapen <github_public@gulfdoctor.net>
License-File: LICENSE
Keywords: python
Classifier: Development Status :: 4 - Beta
Classifier: Intended Audience :: Healthcare Industry
Classifier: Operating System :: OS Independent
Classifier: Programming Language :: Python
Classifier: Programming Language :: Python :: 3
Classifier: Programming Language :: Python :: 3.11
Classifier: Programming Language :: Python :: 3.12
Classifier: Topic :: Scientific/Engineering :: Information Analysis
Classifier: Topic :: Scientific/Engineering :: Medical Science Apps.
Classifier: Topic :: Software Development :: Libraries :: Python Modules
Requires-Python: <4.0,>=3.10
Requires-Dist: click
Requires-Dist: google-cloud-bigquery
Requires-Dist: numpy
Requires-Dist: openpyxl
Requires-Dist: pandas
Requires-Dist: prodict
Requires-Dist: responses
Requires-Dist: timeago
Requires-Dist: tqdm
Provides-Extra: llm
Requires-Dist: langchain; extra == 'llm'
Requires-Dist: langchain-community; extra == 'llm'
Requires-Dist: langchain-huggingface; extra == 'llm'
Requires-Dist: llama-index; extra == 'llm'
Requires-Dist: llama-index-embeddings-langchain; extra == 'llm'
Requires-Dist: llama-index-experimental; extra == 'llm'
Requires-Dist: llama-index-llms-google-genai; extra == 'llm'
Requires-Dist: overrides; extra == 'llm'
